{
  "slug": "lewisham",
  "name": "Lewisham",
  "type": "LB",
  "typeName": "London Borough",
  "onsCode": "E09000023",
  "colour": "hsl(296, 45%, 55%)",
  "initials": "LEW",
  "leader": "",
  "chiefExecutive": "Jennifer Daothong",
  "councillors": 54,
  "website": "https://lewisham.gov.uk",
  "taxBands": {
    "2021": 1744.0,
    "2022": 1817.0,
    "2023": 1926.0,
    "2024": 2038.0,
    "2025": 2135.0,
    "2026": 2237.0
  },
  "taxCurrent": 2135.0,
  "taxPrev": 2038.0,
  "taxChange": 97.0,
  "taxChangePct": 4.8,
  "budgetCategories": [
    {
      "cat": "education",
      "label": "Education",
      "icon": "\ud83d\udcda",
      "amount": 358800.0
    },
    {
      "cat": "adult_social_care",
      "label": "Adult Social Care",
      "icon": "\ud83d\udc74",
      "amount": 117844.0
    },
    {
      "cat": "childrens_social_care",
      "label": "Children's Social Care",
      "icon": "\ud83d\udc76",
      "amount": 108676.0
    },
    {
      "cat": "housing",
      "label": "Housing",
      "icon": "\ud83c\udfe0",
      "amount": 41659.0
    },
    {
      "cat": "public_health",
      "label": "Public Health",
      "icon": "\ud83c\udfe5",
      "amount": 32270.0
    },
    {
      "cat": "environmental",
      "label": "Environment & Streets",
      "icon": "\ud83c\udf33",
      "amount": 31843.0
    },
    {
      "cat": "central_services",
      "label": "Council Running Costs",
      "icon": "\ud83c\udfdb\ufe0f",
      "amount": 17303.0
    },
    {
      "cat": "cultural",
      "label": "Culture & Leisure",
      "icon": "\ud83c\udfad",
      "amount": 13244.0
    },
    {
      "cat": "transport",
      "label": "Roads & Transport",
      "icon": "\ud83d\udee3\ufe0f",
      "amount": 8614.0
    },
    {
      "cat": "planning",
      "label": "Planning & Development",
      "icon": "\ud83d\udcd0",
      "amount": 2652.0
    },
    {
      "cat": "other",
      "label": "Other Services",
      "icon": "\ud83d\udccb",
      "amount": 97.0
    }
  ],
  "budgetTotal": 733002.0,
  "perHousehold": 6664,
  "feedItems": [
    {
      "type": "budget",
      "category": "Adult Social Care",
      "icon": "\ud83d\udc74",
      "amount": 117844.0,
      "perHousehold": 1071,
      "description": "allocated \u00a3117.8m to Adult Social Care (\u2248\u00a31071 per household)",
      "timestamp": "2026-04-22"
    },
    {
      "type": "budget",
      "category": "Housing",
      "icon": "\ud83c\udfe0",
      "amount": 41659.0,
      "perHousehold": 379,
      "description": "allocated \u00a341.7m to Housing (\u2248\u00a3379 per household)",
      "timestamp": "2025-12-12"
    },
    {
      "type": "budget",
      "category": "Education",
      "icon": "\ud83d\udcda",
      "amount": 358800.0,
      "perHousehold": 3262,
      "description": "allocated \u00a3358.8m to Education (\u2248\u00a33262 per household)",
      "timestamp": "2025-11-07"
    },
    {
      "type": "budget",
      "category": "Children's Social Care",
      "icon": "\ud83d\udc76",
      "amount": 108676.0,
      "perHousehold": 988,
      "description": "allocated \u00a3108.7m to Children's Social Care (\u2248\u00a3988 per household)",
      "timestamp": "2025-11-07"
    },
    {
      "type": "tax",
      "category": "Council Tax",
      "icon": "\ud83d\udcc8",
      "amount": 97.0,
      "perHousehold": 97.0,
      "description": "raised Band D council tax by \u00a397 (4.8%) to \u00a32135",
      "timestamp": "2025-03-15"
    }
  ]
}