{
  "slug": "bromsgrove",
  "name": "Bromsgrove District Council",
  "type": "SD",
  "typeName": "District Council",
  "onsCode": "E07000234",
  "region": "West Midlands",
  "colour": "hsl(244, 45%, 55%)",
  "initials": "BRO",
  "leader": "Cllr Karen May",
  "chiefExecutive": "John Leach (Shared with Redditch)",
  "councillors": 31,
  "website": "https://www.bromsgrove.gov.uk",
  "taxBands": {
    "2021": 1933.0,
    "2022": 2002.0,
    "2023": 2097.0,
    "2024": 2196.0,
    "2025": 2303.0,
    "2026": 2479.0
  },
  "taxCurrent": 2303.0,
  "taxPrev": 2196.0,
  "taxChange": 107.0,
  "taxChangePct": 4.9,
  "budgetCategories": [
    {
      "cat": "central_services",
      "label": "Council Running Costs",
      "icon": "\ud83c\udfdb\ufe0f",
      "amount": 6659.0,
      "description": "Council tax collection, HR, finance, IT, legal services, and democratic governance.",
      "perCapita": 65.5
    },
    {
      "cat": "environmental",
      "label": "Environment & Streets",
      "icon": "\ud83c\udf33",
      "amount": 3889.0,
      "description": "Waste collection and recycling, street cleaning, environmental health, and regulatory services.",
      "perCapita": 38.2
    },
    {
      "cat": "housing",
      "label": "Housing",
      "icon": "\ud83c\udfe0",
      "amount": 1709.0,
      "description": "Housing benefit, homelessness services, council housing management, and affordable housing programmes.",
      "perCapita": 16.8
    },
    {
      "cat": "planning",
      "label": "Planning & Development",
      "icon": "\ud83d\udcd0",
      "amount": 1538.0,
      "description": "Planning applications, building control, economic development, and regeneration projects.",
      "perCapita": 15.1
    },
    {
      "cat": "cultural",
      "label": "Culture & Leisure",
      "icon": "\ud83c\udfad",
      "amount": 696.0,
      "description": "Libraries, museums, parks, leisure centres, sports facilities, and arts programmes.",
      "perCapita": 6.8
    },
    {
      "cat": "transport",
      "label": "Roads & Transport",
      "icon": "\ud83d\udee3\ufe0f",
      "amount": 623.0,
      "description": "Road maintenance, public transport subsidies, street lighting, and transport planning.",
      "perCapita": 6.1
    }
  ],
  "budgetTotal": 15114.0,
  "population": 101685,
  "populationYear": 2024,
  "perCapita": 149,
  "perHousehold": 302,
  "feedItems": [
    {
      "type": "budget",
      "category": "Planning & Development",
      "icon": "\ud83d\udcd0",
      "amount": 1538.0,
      "perCapita": 15,
      "perHousehold": 31,
      "description": "allocated \u00a31.5m to Planning & Development (\u2248\u00a315 per resident)",
      "timestamp": "2026-03-15"
    },
    {
      "type": "budget",
      "category": "Council Running Costs",
      "icon": "\ud83c\udfdb\ufe0f",
      "amount": 6659.0,
      "perCapita": 65,
      "perHousehold": 133,
      "description": "allocated \u00a36.7m to Council Running Costs (\u2248\u00a365 per resident)",
      "timestamp": "2026-01-24"
    },
    {
      "type": "budget",
      "category": "Housing",
      "icon": "\ud83c\udfe0",
      "amount": 1709.0,
      "perCapita": 17,
      "perHousehold": 34,
      "description": "allocated \u00a31.7m to Housing (\u2248\u00a317 per resident)",
      "timestamp": "2026-01-06"
    },
    {
      "type": "budget",
      "category": "Environment & Streets",
      "icon": "\ud83c\udf33",
      "amount": 3889.0,
      "perCapita": 38,
      "perHousehold": 78,
      "description": "allocated \u00a33.9m to Environment & Streets (\u2248\u00a338 per resident)",
      "timestamp": "2025-07-09"
    },
    {
      "type": "tax",
      "category": "Council Tax",
      "icon": "\ud83d\udcc8",
      "amount": 107.0,
      "perCapita": 107.0,
      "perHousehold": 107.0,
      "description": "raised Band D council tax by \u00a3107 (4.9%) to \u00a32303",
      "timestamp": "2025-03-15"
    }
  ]
}