{
  "slug": "northumberland",
  "name": "Northumberland Council",
  "type": "UA",
  "typeName": "Unitary Authority",
  "onsCode": "E06000057",
  "colour": "hsl(108, 45%, 55%)",
  "initials": "NOR",
  "leader": "",
  "chiefExecutive": "Helen Paterson",
  "councillors": 134,
  "website": "https://www.northumberland.gov.uk",
  "taxBands": {
    "2021": 2055.0,
    "2022": 2142.0,
    "2023": 2248.0,
    "2024": 2355.0,
    "2025": 2465.0,
    "2026": 2597.0
  },
  "taxCurrent": 2465.0,
  "taxPrev": 2355.0,
  "taxChange": 110.0,
  "taxChangePct": 4.7,
  "budgetCategories": [
    {
      "cat": "education",
      "label": "Education",
      "icon": "\ud83d\udcda",
      "description": "Schools, special educational needs and learning services.",
      "amount": 214876.0,
      "perCapita": 648.3
    },
    {
      "cat": "adult_social_care",
      "label": "Adult Social Care",
      "icon": "\ud83d\udc74",
      "description": "Care and support for older and disabled adults.",
      "amount": 144583.0,
      "perCapita": 436.3
    },
    {
      "cat": "childrens_social_care",
      "label": "Children's Social Care",
      "icon": "\ud83d\udc76",
      "description": "Support and safeguarding for children, young people and families.",
      "amount": 62580.0,
      "perCapita": 188.8
    },
    {
      "cat": "environmental",
      "label": "Environment & Streets",
      "icon": "\ud83c\udf33",
      "description": "Waste, street cleaning, parks and environmental health.",
      "amount": 38106.0,
      "perCapita": 115.0
    },
    {
      "cat": "public_health",
      "label": "Public Health",
      "icon": "\ud83c\udfe5",
      "description": "Services that help people stay healthy and prevent illness.",
      "amount": 19951.0,
      "perCapita": 60.2
    },
    {
      "cat": "central_services",
      "label": "Council Running Costs",
      "icon": "\ud83c\udfdb\ufe0f",
      "description": "Core staff, finance, IT, legal and democratic services.",
      "amount": 17469.0,
      "perCapita": 52.7
    },
    {
      "cat": "cultural",
      "label": "Culture & Leisure",
      "icon": "\ud83c\udfad",
      "description": "Libraries, museums, sports, arts and leisure services.",
      "amount": 14298.0,
      "perCapita": 43.1
    },
    {
      "cat": "transport",
      "label": "Roads & Transport",
      "icon": "\ud83d\udee3\ufe0f",
      "description": "Road maintenance, public transport and local travel.",
      "amount": 11863.0,
      "perCapita": 35.8
    },
    {
      "cat": "housing",
      "label": "Housing",
      "icon": "\ud83c\udfe0",
      "description": "Housing advice, homelessness support and council homes.",
      "amount": 3482.0,
      "perCapita": 10.5
    },
    {
      "cat": "planning",
      "label": "Planning & Development",
      "icon": "\ud83d\udcd0",
      "description": "Planning applications, building control and local development.",
      "amount": 3197.0,
      "perCapita": 9.6
    }
  ],
  "budgetTotal": 530405.0,
  "population": 331420,
  "populationYear": 2024,
  "perCapita": 1600,
  "perHousehold": 5304,
  "feedItems": [
    {
      "type": "budget",
      "category": "Education",
      "icon": "\ud83d\udcda",
      "amount": 214876.0,
      "perCapita": 648,
      "description": "allocated \u00a3214.9m to Education (\u2248\u00a3648 per resident)",
      "timestamp": "2026-06-01"
    },
    {
      "type": "budget",
      "category": "Adult Social Care",
      "icon": "\ud83d\udc74",
      "amount": 144583.0,
      "perCapita": 436,
      "description": "allocated \u00a3144.6m to Adult Social Care (\u2248\u00a3436 per resident)",
      "timestamp": "2026-05-08"
    },
    {
      "type": "budget",
      "category": "Environment & Streets",
      "icon": "\ud83c\udf33",
      "amount": 38106.0,
      "perCapita": 115,
      "description": "allocated \u00a338.1m to Environment & Streets (\u2248\u00a3115 per resident)",
      "timestamp": "2026-03-15"
    },
    {
      "type": "budget",
      "category": "Children's Social Care",
      "icon": "\ud83d\udc76",
      "amount": 62580.0,
      "perCapita": 189,
      "description": "allocated \u00a362.6m to Children's Social Care (\u2248\u00a3189 per resident)",
      "timestamp": "2026-02-10"
    },
    {
      "type": "tax",
      "category": "Council Tax",
      "icon": "\ud83d\udcc8",
      "amount": 110.0,
      "perCapita": 110.0,
      "description": "raised Band D council tax by \u00a3110 (4.7%) to \u00a32465",
      "timestamp": "2025-03-15"
    }
  ]
}